nnfasta/__init__.py
nnfasta/fasta.py
nnfasta/py.typed
nnfasta-0.1.36.dist-info/LICENSE
nnfasta-0.1.36.dist-info/METADATA
nnfasta-0.1.36.dist-info/WHEEL
nnfasta-0.1.36.dist-info/RECORD
