Metadata-Version: 2.1
Name: nnfasta
Version: 0.1.36
Summary: Lightweight Neural Net efficient FASTA
Home-page: https://github.com/arabidopsis/nnfasta.git
License: MIT
Keywords: fasta,torch,tensorflow,neural nets,training
Author: Ian Castleden
Author-email: ian.castleden@uwa.edu.au
Requires-Python: >=3.9
Classifier: Development Status :: 4 - Beta
Classifier: Intended Audience :: Science/Research
Classifier: License :: OSI Approved :: MIT License
Classifier: Programming Language :: Python :: 3
Classifier: Programming Language :: Python :: 3.9
Classifier: Programming Language :: Python :: 3.10
Classifier: Programming Language :: Python :: 3.11
Classifier: Programming Language :: Python :: 3.12
Classifier: Programming Language :: Python :: 3 :: Only
Classifier: Topic :: Scientific/Engineering :: Bio-Informatics
Project-URL: Repository, https://github.com/arabidopsis/nnfasta.git
